HTSeq/_HTSeq_internal.py
HTSeq/StepVector.py
HTSeq/_version.py
HTSeq/__init__.py
HTSeq/utils.py
HTSeq/features.py
HTSeq/_StepVector.cpython-39-x86_64-linux-gnu.so
HTSeq/StretchVector.py
HTSeq/_HTSeq.cpython-39-x86_64-linux-gnu.so
HTSeq/scripts/qa.py
HTSeq/scripts/count.py
HTSeq/scripts/count_with_barcodes.py
HTSeq/scripts/__init__.py
HTSeq/scripts/utils.py
HTSeq/scripts/count_features/reads_stats.py
HTSeq/scripts/count_features/count_features_per_file.py
HTSeq/scripts/count_features/__init__.py
HTSeq/scripts/count_features/reads_io_processor.py
HTSeq-2.0.9.dist-info/LICENSE
HTSeq-2.0.9.dist-info/METADATA
HTSeq-2.0.9.dist-info/top_level.txt
HTSeq-2.0.9.dist-info/RECORD
HTSeq-2.0.9.dist-info/WHEEL
HTSeq-2.0.9.data/scripts/htseq-count
HTSeq-2.0.9.data/scripts/htseq-qa
HTSeq-2.0.9.data/scripts/htseq-count-barcodes
