Metadata-Version: 2.1
Name: HTSeq
Version: 2.0.9
Summary: A framework to process and analyze data from high-throughput sequencing (HTS) assays
Home-page: https://github.com/htseq
Author: Simon Anders, Fabio Zanini
Author-email: fabio.zanini@unsw.edu.au
Maintainer: Fabio Zanini
Maintainer-email: fabio.zanini@unsw.edu.au
License: GPL3
Classifier: Development Status :: 5 - Production/Stable
Classifier: Topic :: Scientific/Engineering :: Bio-Informatics
Classifier: Intended Audience :: Developers
Classifier: Intended Audience :: Science/Research
Classifier: License :: OSI Approved :: GNU General Public License (GPL)
Classifier: Operating System :: POSIX
Classifier: Programming Language :: Python
License-File: LICENSE
Requires-Dist: numpy
Requires-Dist: pysam
Provides-Extra: htseq-qa
Requires-Dist: matplotlib>=1.4; extra == "htseq-qa"
Provides-Extra: test
Requires-Dist: scipy>=1.5.0; extra == "test"
Requires-Dist: pytest>=6.2.5; extra == "test"
Requires-Dist: pandas>=1.1.0; extra == "test"
Requires-Dist: matplotlib>=1.4; extra == "test"
